{
    "id": "region_na",
    "category": "region",
    "name": "North America",
    "culture_notes": [
        "Native TikTok/Reels style text boxes (white text, black or colored background blocks).",
        "Inclusion of western pop-culture meme cuts (e.g., confused math lady, doge, brain expanding). Looks like amateur, raw UGC content.",
        "Attention-deficit friendly. Reset the visual frame every 2-3 seconds to hold retention."
    ],
    "preferred_bgm": "Meme/Trending TikTok audio",
    "focus": "Frustration & Easy win"
}